cosimpy/EM_Field.py
cosimpy/Exceptions.py
cosimpy/RF_Coil.py
cosimpy/S_Matrix.py
cosimpy/__init__.py
cosimpy-2.0.0.dist-info/licenses/LICENSE
cosimpy-2.0.0.dist-info/METADATA
cosimpy-2.0.0.dist-info/WHEEL
cosimpy-2.0.0.dist-info/top_level.txt
cosimpy-2.0.0.dist-info/RECORD
