Metadata-Version: 2.4
Name: cosimpy
Version: 2.0.0
Summary: Python electromagnetic co-simulation library
Home-page: https://umbertozanovello.github.io/CoSimPy/
Author: Umberto Zanovello
Author-email: umbertozanovello@hotmail.com
Classifier: Programming Language :: Python :: 3
Classifier: License :: OSI Approved :: MIT License
Classifier: Operating System :: OS Independent
Requires-Python: >=3.5
License-File: LICENSE
Requires-Dist: numpy>=2.0.0
Requires-Dist: matplotlib>=3.9.0
Requires-Dist: h5py>=3.11.0
Requires-Dist: scipy>=1.14.0
Dynamic: license-file
